{
  "_id": "appDeathCoffer01",
  "img": "systems/pf2e/icons/default-icons/equipment.svg",
  "name": "Death's Head Coffer",
  "type": "equipment",
  "folder": "appItemFolder001",
  "sort": 0,
  "ownership": {
    "default": 0
  },
  "flags": {},
  "_stats": {
    "systemId": "pf2e",
    "systemVersion": "8.2.0",
    "coreVersion": "14.363",
    "compendiumSource": null,
    "duplicateSource": null,
    "exportSource": null,
    "createdTime": 0,
    "modifiedTime": 0,
    "lastModifiedBy": null
  },
  "system": {
    "baseItem": null,
    "bulk": {
      "value": 0.1
    },
    "containerId": null,
    "description": {
      "value": "<p><strong>Ch.2's infection vector</strong> (Appendix 5; 1,000 gp → 100 gp). A skull-chased metal coffer about the size of two fists. <strong>Single use:</strong> while the lid is closed, the contents (up to Tiny) hang in stasis — no aging, no decay, no damage — and any infectious matter stays viable.</p><ul><li><strong>Plague box:</strong> seal items in with a disease source and every item inside becomes a carrier; for 1 week after removal, touching a carried item forces a save against that disease (blood veil, for the cult's coin-shipments).</li><li>Opening the coffer ends the magic forever (it becomes a mundane box). Some are locked: @Check[type:thievery|dc:30] to pick.</li></ul>"
    },
    "equipped": {
      "carryType": "worn",
      "handsHeld": 0,
      "invested": null
    },
    "hardness": 0,
    "hp": {
      "max": 0,
      "value": 0
    },
    "level": {
      "value": 4
    },
    "material": {
      "grade": null,
      "type": null
    },
    "price": {
      "value": {
        "gp": 100
      }
    },
    "publication": {
      "title": "Pathfinder: Curse of the Crimson Throne (PF2e conversion, private)",
      "authors": "",
      "license": "OGL",
      "remaster": true
    },
    "quantity": 1,
    "rules": [],
    "size": "med",
    "slug": null,
    "traits": {
      "rarity": "rare",
      "value": [
        "magical",
        "consumable"
      ]
    },
    "usage": {
      "value": "worn"
    }
  },
  "_key": "!items!appDeathCoffer01"
}
