{
  "_id": "fxCrownWhisper01",
  "img": "systems/pf2e/icons/equipment/treasure/art-objects/major-art-object/jeweled-mithral-crown.webp",
  "name": "Effect: Whispers of the Crown",
  "type": "effect",
  "effects": [],
  "folder": "appItemFolder001",
  "sort": 0,
  "ownership": {
    "default": 0
  },
  "flags": {},
  "_stats": {
    "systemId": "pf2e",
    "systemVersion": "8.2.0",
    "coreVersion": "14.363",
    "compendiumSource": null,
    "duplicateSource": null,
    "exportSource": null,
    "createdTime": 0,
    "modifiedTime": 0,
    "lastModifiedBy": null
  },
  "system": {
    "description": {
      "value": "<p>The corruption-clock carrier for @UUID[Compendium.cotct-pf2e-conversion.cotct-items.Item.crownOfFangs0001]{The Crown of Fangs}: a <strong>non-Ileosa wearer</strong> attempts @Check[type:will|dc:40] per week worn or the whispers take root — the soul-seed of Kazavon begins the campaign's horror over again in a new vessel.</p><p>Apply this effect to any non-Ileosa creature that invests the crown; tick the badge up each week worn (it tracks failed saves at the GM's preference). The second soul grows with every day worn and every death defied. The crown's own @Check[type:will|dc:42] dominate (3/day) and its sunder profile live on the item doc.</p>"
    },
    "duration": {
      "expiry": null,
      "sustained": false,
      "unit": "unlimited",
      "value": -1
    },
    "level": {
      "value": 22
    },
    "publication": {
      "title": "Pathfinder: Curse of the Crimson Throne (PF2e conversion, private)",
      "authors": "",
      "license": "OGL",
      "remaster": true
    },
    "rules": [],
    "start": {
      "initiative": null,
      "value": 0
    },
    "tokenIcon": {
      "show": true
    },
    "traits": {
      "value": []
    },
    "slug": "effect-whispers-of-the-crown",
    "badge": {
      "max": 99,
      "min": 1,
      "type": "counter",
      "value": 1
    }
  },
  "_key": "!items!fxCrownWhisper01"
}
